setup.py
src/jldssdp/__init__.py
src/jldssdp/do_checks.py
src/jldssdp/do_setup.py
src/jldssdp/helpers.py
src/jldssdp/protocol.py
src/jldssdp/script_discover.py
src/jldssdp/script_notify.py
src/jldssdp/tools_sys.py
src/jldssdp.egg-info/PKG-INFO
src/jldssdp.egg-info/SOURCES.txt
src/jldssdp.egg-info/dependency_links.txt
src/jldssdp.egg-info/not-zip-safe
src/jldssdp.egg-info/requires.txt
src/jldssdp.egg-info/top_level.txt
src/scripts/jldssdp-discover
src/scripts/jldssdp-notify