Metadata-Version: 1.0
Name: jldssdp
Version: 0.2
Summary: Collection of SSDP related tools
Home-page: https://github.com/jldupont/jldssdp
Author: Jean-Lou Dupont
Author-email: jl@jldupont.com
License: UNKNOWN
Platform: UNKNOWN
